MANIFEST.in
README.md
setup.py
django_statistic.egg-info/PKG-INFO
django_statistic.egg-info/SOURCES.txt
django_statistic.egg-info/dependency_links.txt
django_statistic.egg-info/not-zip-safe
django_statistic.egg-info/top_level.txt
statistic/__init__.py
statistic/models.py
statistic/settings.py